MANIFEST.in
README.md
requirements.txt
setup.py
cmd_command/__init__.py
cmd_command/agent_configuration.py
harp_gate_client/__init__.py
harp_gate_client/app.py
harp_gate_client.egg-info/PKG-INFO
harp_gate_client.egg-info/SOURCES.txt
harp_gate_client.egg-info/dependency_links.txt
harp_gate_client.egg-info/entry_points.txt
harp_gate_client.egg-info/not-zip-safe
harp_gate_client.egg-info/requires.txt
harp_gate_client.egg-info/top_level.txt
harp_gate_client/endpoints/__init__.py
harp_gate_client/endpoints/notifications.py
harp_gate_client/logic/__init__.py
harp_gate_client/logic/config_update.py
harp_gate_client/models/__init__.py
harp_gate_client/notifications_collectors/__init__.py
harp_gate_client/notifications_collectors/icinga_collector.py
harp_gate_client/notifications_collectors/push_notification.py
harp_gate_client/notifications_collectors/zabbix_collector.py
harp_gate_client/settings/__init__.py
harp_gate_client/settings/app_settings.py