Metadata-Version: 1.2
Name: harp-gate-client
Version: 1.0.26
Summary: Harp Gate Client
Home-page: UNKNOWN
Author: 
Author-email: 
License: UNKNOWN
Platform: UNKNOWN
Requires-Python: >3.7.0
